CHANGES.rst
MANIFEST.in
README.rst
setup.py
PrintOnline/PrintOnline.bat
PrintOnline/PrintOnline.py
PrintOnline/PrintOnline.pyc
PrintOnline/__init__.py
PrintOnline/__init__.pyc
PrintOnline/__main__.py
PrintOnline/index.html
PrintOnline/wsgi.py
PrintOnline/wsgi.pyc
PrintOnline.egg-info/PKG-INFO
PrintOnline.egg-info/SOURCES.txt
PrintOnline.egg-info/dependency_links.txt
PrintOnline.egg-info/not-zip-safe
PrintOnline.egg-info/top_level.txt
PrintOnline/static/angular.min.js
PrintOnline/static/checked.png
PrintOnline/static/jquery-1.7.2.min.js
PrintOnline/static/jquery.form.min.js
PrintOnline/static/unchecked.png