Metadata-Version: 1.1
Name: PrintOnline
Version: 0.0.3
Summary: A online printer manager for Windows.
Home-page: https://github.com/sintrb/PrintOnline
Author: sintrb
Author-email: sintrb@gmail.com
License: Apache
Keywords: svn,svn client,svn online
Platform: UNKNOWN
Classifier: Intended Audience :: End Users/Desktop
Classifier: Operating System :: Microsoft :: Windows
Classifier: Programming Language :: Python :: 2.7
